.gitignore
CHANGES.txt
CONTRIBUTORS.txt
MANIFEST.in
README.rst
bootstrap.py
buildout.cfg
setup.cfg
setup.py
docs/LICENSE.GPL
docs/LICENSE.txt
src/collective/__init__.py
src/collective.groupmail.egg-info/PKG-INFO
src/collective.groupmail.egg-info/SOURCES.txt
src/collective.groupmail.egg-info/dependency_links.txt
src/collective.groupmail.egg-info/entry_points.txt
src/collective.groupmail.egg-info/namespace_packages.txt
src/collective.groupmail.egg-info/not-zip-safe
src/collective.groupmail.egg-info/paster_plugins.txt
src/collective.groupmail.egg-info/requires.txt
src/collective.groupmail.egg-info/top_level.txt
src/collective/groupmail/__init__.py
src/collective/groupmail/configure.zcml
src/collective/groupmail/testing.py
src/collective/groupmail/browser/__init__.py
src/collective/groupmail/browser/configure.zcml
src/collective/groupmail/browser/groupview.pt
src/collective/groupmail/browser/groupview.py
src/collective/groupmail/templates/Products.CMFPlone.skins.plone_forms.member_search_form.pt
src/collective/groupmail/templates/Products.CMFPlone.skins.plone_forms.member_search_results.pt
src/collective/groupmail/tests/__init__.py
src/collective/groupmail/tests/test_permissions.py