Metadata-Version: 1.1
Name: collective.groupmail
Version: 1.1
Summary: Send feedback email to groups in Plone
Home-page: http://svn.plone.org/svn/collective/
Author: Lennart Regebro
Author-email: regebro@gmail.com
License: gpl
Keywords: plone group email
Platform: UNKNOWN
Classifier: Programming Language :: Python :: 2.6
Classifier: Framework :: Plone :: 4.1
